libtukaan/__init__.py
libtukaan/serif.py
libtukaan/xcursor.py
libtukaan/unix/libserif_x64.so
libtukaan/unix/libtkxcursor_x64.so
libtukaan_unix-0.1.5.dist-info/METADATA
libtukaan_unix-0.1.5.dist-info/WHEEL
libtukaan_unix-0.1.5.dist-info/top_level.txt
libtukaan_unix-0.1.5.dist-info/RECORD
